pyqt_reactive/__init__.py
pyqt_reactive/animation/__init__.py
pyqt_reactive/animation/flash_config.py
pyqt_reactive/animation/flash_mixin.py
pyqt_reactive/animation/flash_overlay_opengl.py
pyqt_reactive/core/__init__.py
pyqt_reactive/core/background_task.py
pyqt_reactive/core/code_generator.py
pyqt_reactive/core/collapsible_splitter_helper.py
pyqt_reactive/core/debounce_timer.py
pyqt_reactive/core/log_utils.py
pyqt_reactive/core/path_cache.py
pyqt_reactive/core/performance_monitor.py
pyqt_reactive/core/reorderable_list_widget.py
pyqt_reactive/core/rich_text_appender.py
pyqt_reactive/core/sort_utils.py
pyqt_reactive/dialogs/__init__.py
pyqt_reactive/dialogs/group_by_selector_dialog.py
pyqt_reactive/forms/__init__.py
pyqt_reactive/forms/form_init_service.py
pyqt_reactive/forms/layout_constants.py
pyqt_reactive/forms/parameter_form_base.py
pyqt_reactive/forms/parameter_form_constants.py
pyqt_reactive/forms/parameter_form_manager.py
pyqt_reactive/forms/parameter_form_service.py
pyqt_reactive/forms/parameter_info_types.py
pyqt_reactive/forms/parameter_type_utils.py
pyqt_reactive/forms/ui_utils.py
pyqt_reactive/forms/widget_creation_config.py
pyqt_reactive/forms/widget_creation_registry.py
pyqt_reactive/forms/widget_creation_types.py
pyqt_reactive/forms/widget_dispatcher.py
pyqt_reactive/forms/widget_factory.py
pyqt_reactive/forms/widget_operations.py
pyqt_reactive/forms/widget_registry.py
pyqt_reactive/forms/widget_strategies.py
pyqt_reactive/io/base.py
pyqt_reactive/io/defaults.py
pyqt_reactive/io/exceptions.py
pyqt_reactive/io/file_manager.py
pyqt_reactive/protocols/__init__.py
pyqt_reactive/protocols/codegen_provider.py
pyqt_reactive/protocols/component_selection.py
pyqt_reactive/protocols/form_config.py
pyqt_reactive/protocols/function_registry.py
pyqt_reactive/protocols/llm_service.py
pyqt_reactive/protocols/log_providers.py
pyqt_reactive/protocols/preview_formatter.py
pyqt_reactive/protocols/widget_adapters.py
pyqt_reactive/protocols/widget_protocols.py
pyqt_reactive-0.1.6.dist-info/METADATA
pyqt_reactive-0.1.6.dist-info/WHEEL
pyqt_reactive-0.1.6.dist-info/licenses/LICENSE
pyqt_reactive-0.1.6.dist-info/RECORD
