Metadata-Version: 2.4
Name: pyqt-reactive
Version: 0.1.6
Summary: React-quality reactive form generation framework for PyQt6
Project-URL: Homepage, https://github.com/OpenHCSDev/pyqt-reactive
Project-URL: Documentation, https://pyqt-reactive.readthedocs.io
Project-URL: Repository, https://github.com/OpenHCSDev/pyqt-reactive
Project-URL: Issues, https://github.com/OpenHCSDev/pyqt-reactive/issues
Author-email: Tristan Simas <tristan.simas@mail.mcgill.ca>
License: MIT
License-File: LICENSE
Keywords: dataclass,forms,gui,pyqt6,reactive,widgets
Classifier: Development Status :: 4 - Beta
Classifier: Intended Audience :: Developers
Classifier: License :: OSI Approved :: MIT License
Classifier: Programming Language :: Python :: 3
Classifier: Programming Language :: Python :: 3.11
Classifier: Programming Language :: Python :: 3.12
Classifier: Programming Language :: Python :: 3.13
Classifier: Topic :: Software Development :: Libraries :: Python Modules
Classifier: Topic :: Software Development :: User Interfaces
Requires-Python: >=3.11
Requires-Dist: objectstate>=0.1.0
Requires-Dist: pyqt6>=6.4.0
Requires-Dist: python-introspect>=0.1.0
Provides-Extra: dev
Requires-Dist: black>=23.0; extra == 'dev'
Requires-Dist: mypy>=1.0; extra == 'dev'
Requires-Dist: pytest-cov>=4.0; extra == 'dev'
Requires-Dist: pytest-qt>=4.0; extra == 'dev'
Requires-Dist: pytest>=7.0; extra == 'dev'
Requires-Dist: ruff>=0.1.0; extra == 'dev'
Provides-Extra: docs
Requires-Dist: sphinx-autodoc-typehints>=1.25; extra == 'docs'
Requires-Dist: sphinx-rtd-theme>=2.0; extra == 'docs'
Requires-Dist: sphinx>=7.0; extra == 'docs'
Provides-Extra: magicgui
Requires-Dist: magicgui>=0.7.0; extra == 'magicgui'
